lazycook/__init__.py
lazycook/__main__.py
lazycook/lazycook.py
lazycook-1.2.1.dist-info/METADATA
lazycook-1.2.1.dist-info/WHEEL
lazycook-1.2.1.dist-info/top_level.txt
lazycook-1.2.1.dist-info/RECORD
