Metadata-Version: 2.4
Name: lazycook
Version: 1.2.1
Summary: LazyCook is an autonomous multi-agent conversational assistant designed to intelligently process user queries, manage documents, store conversations, and maintain iterative AI reasoning loops. It uses Gemini 2.5 Flash model with a four-agent architecture for high-quality responses and continuous learning.
Author: Hitarth Trivedi(Alpha.Kore),Harsh Bhatt(Alpha.Kore)
Author-email: "Hitarth Trivedi (Alpha.Kore)" <hitartht318@gmail.com>, "Harsh Bhatt (Alpha.Kore)" <bhattharsh328@gmail.com>
Maintainer: Hitarth Trivedi(Alpha.Kore),Harsh Bhatt(Alpha.Kore)
Maintainer-email: "Hitarth Trivedi (Alpha.Kore)" <hitartht318@gmail.com>, "Harsh Bhatt (Alpha.Kore)" <bhattharsh328@gmail.com>
Project-URL: Homepage, https://github.com/HitarthTrivedi/lazycook
Classifier: Programming Language :: Python :: 3
Classifier: Programming Language :: Python :: 3.10
Classifier: Programming Language :: Python :: 3.11
Classifier: Programming Language :: Python :: 3.12
Classifier: Operating System :: OS Independent
Requires-Python: >=3.10
Requires-Dist: PyPDF2==3.0.1
Requires-Dist: google-generativeai>=0.3.2
Requires-Dist: rich>=13.7.0
Requires-Dist: python-docx>=1.1.0
Requires-Dist: matplotlib>=3.8.0
Requires-Dist: pandas>=2.1.0
Requires-Dist: seaborn>=0.13.0
Requires-Dist: numpy>=1.26.0
Dynamic: author
Dynamic: maintainer
Dynamic: requires-python
